biorobot/__init__.py
biorobot/brittle_star/__init__.py
biorobot/brittle_star/environment/__init__.py
biorobot/brittle_star/environment/directed_locomotion/__init__.py
biorobot/brittle_star/environment/directed_locomotion/dual.py
biorobot/brittle_star/environment/directed_locomotion/mjc_env.py
biorobot/brittle_star/environment/directed_locomotion/mjx_env.py
biorobot/brittle_star/environment/directed_locomotion/shared.py
biorobot/brittle_star/environment/light_escape/__init__.py
biorobot/brittle_star/environment/light_escape/dual.py
biorobot/brittle_star/environment/light_escape/mjc_env.py
biorobot/brittle_star/environment/light_escape/mjx_env.py
biorobot/brittle_star/environment/light_escape/shared.py
biorobot/brittle_star/environment/shared/__init__.py
biorobot/brittle_star/environment/shared/base.py
biorobot/brittle_star/environment/shared/observables.py
biorobot/brittle_star/environment/undirected_locomotion/__init__.py
biorobot/brittle_star/environment/undirected_locomotion/dual.py
biorobot/brittle_star/environment/undirected_locomotion/mjc_env.py
biorobot/brittle_star/environment/undirected_locomotion/mjx_env.py
biorobot/brittle_star/environment/undirected_locomotion/shared.py
biorobot/brittle_star/mjcf/__init__.py
biorobot/brittle_star/mjcf/arena/__init__.py
biorobot/brittle_star/mjcf/arena/aquarium.py
biorobot/brittle_star/mjcf/arena/target.py
biorobot/brittle_star/mjcf/morphology/__init__.py
biorobot/brittle_star/mjcf/morphology/morphology.py
biorobot/brittle_star/mjcf/morphology/parts/__init__.py
biorobot/brittle_star/mjcf/morphology/parts/arm.py
biorobot/brittle_star/mjcf/morphology/parts/arm_segment.py
biorobot/brittle_star/mjcf/morphology/parts/disk.py
biorobot/brittle_star/mjcf/morphology/specification/__init__.py
biorobot/brittle_star/mjcf/morphology/specification/default.py
biorobot/brittle_star/mjcf/morphology/specification/specification.py
biorobot/brittle_star/tests/__init__.py
biorobot/brittle_star/tests/main.py
biorobot-0.4.1.dist-info/licenses/LICENSE
biorobot-0.4.1.dist-info/METADATA
biorobot-0.4.1.dist-info/WHEEL
biorobot-0.4.1.dist-info/top_level.txt
biorobot-0.4.1.dist-info/RECORD
