Metadata-Version: 2.4
Name: biorobot
Version: 0.4.1
Summary: The Bio-inspired Robotics Testbed (BRT).
Home-page: https://github.com/Co-Evolve/brb
Author-email: Dries Marzougui <dries.marzougui@gmail.com>
License: MIT
Project-URL: Homepage, https://github.com/Co-Evolve/brt
Project-URL: Repository, https://github.com/Co-Evolve/brt
Classifier: Development Status :: 5 - Production/Stable
Classifier: Intended Audience :: Developers
Classifier: Intended Audience :: Science/Research
Classifier: Natural Language :: English
Classifier: Programming Language :: Python :: 3
Classifier: Programming Language :: Python :: 3.8
Classifier: Programming Language :: Python :: 3.9
Classifier: Programming Language :: Python :: 3.10
Classifier: Programming Language :: Python :: 3.11
Classifier: Programming Language :: Python :: 3.12
Classifier: Topic :: Scientific/Engineering
Requires-Python: >=3.8
License-File: LICENSE
Requires-Dist: chex
Requires-Dist: dm-control
Requires-Dist: fprs
Requires-Dist: gymnasium
Requires-Dist: mujoco
Requires-Dist: mujoco-mjx
Requires-Dist: moojoco
Requires-Dist: numpy
Requires-Dist: opencv-python
Requires-Dist: pillow
Requires-Dist: transforms3d
Dynamic: home-page
Dynamic: license-file
